DjangoAsyncMail/__init__.py
DjangoAsyncMail/admin.py
DjangoAsyncMail/apps.py
DjangoAsyncMail/mail.py
DjangoAsyncMail/models.py
DjangoAsyncMail/tests.py
DjangoAsyncMail/views.py
DjangoAsyncMail-0.1.dist-info/LICENSE
DjangoAsyncMail-0.1.dist-info/METADATA
DjangoAsyncMail-0.1.dist-info/WHEEL
DjangoAsyncMail-0.1.dist-info/top_level.txt
DjangoAsyncMail-0.1.dist-info/RECORD
