Metadata-Version: 2.1
Name: DjangoAsyncMail
Version: 0.1
Summary: A Django app to send email asynchronously
Home-page: https://github.com/Jayesh-Mahato/DjangoAsyncMail
Author: Jayesh Mahato
Author-email: jayesh.mahato@gmail.com
License: BSD-3-Clause
Project-URL: Bug Tracker, https://github.com/Jayesh-Mahato/DjangoAsyncEmail/issues
Platform: UNKNOWN
Classifier: Environment :: Web Environment
Classifier: Framework :: Django
Classifier: Framework :: Django :: 4.0
Classifier: Intended Audience :: Developers
Classifier: License :: OSI Approved :: BSD License
Classifier: Operating System :: OS Independent
Classifier: Programming Language :: Python :: 3
Classifier: Programming Language :: Python :: 3.10
Requires-Python: >=3.8
License-File: LICENSE
Requires-Dist: Django (>=4.0)
